pyBlang/__init__.py
pyBlang/diagnostics.py
pyBlang/model.py
pyBlang/plots.py
pyBlang/result.py
pyBlang/utils.py
pyBlang/variable.py
pyBlang/tests/__init__.py
pyBlang/tests/test_model.py
pyBlang/tests/test_result.py
pyBlang/tests/test_variable.py
pyBlang-0.1.1.dist-info/LICENSE
pyBlang-0.1.1.dist-info/METADATA
pyBlang-0.1.1.dist-info/WHEEL
pyBlang-0.1.1.dist-info/top_level.txt
pyBlang-0.1.1.dist-info/RECORD
