Metadata-Version: 2.1
Name: pyBlang
Version: 0.1.1
Summary: A python package to run Blang CLI commands and streamline usage through python.
Home-page: UNKNOWN
Author: Sahand Hosseini
Author-email: 
License: UNKNOWN
Platform: UNKNOWN
Requires-Dist: matplotlib
Requires-Dist: seaborn
Requires-Dist: pandas
Requires-Dist: numpy
